indicnlp/RESOURCES/script/all_script_phonetic_data.csv
indicnlp/RESOURCES/script/english_arpabet_list.csv
indicnlp/RESOURCES/script/english_script_phonetic_data.csv
indicnlp/RESOURCES/script/tamil_script_phonetic_data.csv
indicnlp/RESOURCES/transliterate/offset_itrans_map.csv
indicnlp/__init__.py
indicnlp/common.py
indicnlp/langinfo.py
indicnlp/loader.py
indicnlp/normalize/__init__.py
indicnlp/normalize/indic_normalize.py
indicnlp/script/__init__.py
indicnlp/script/english_script.py
indicnlp/script/indic_scripts.py
indicnlp/script/phonetic_sim.py
indicnlp/tokenize/__init__.py
indicnlp/tokenize/indic_detokenize.py
indicnlp/tokenize/indic_tokenize.py
indicnlp/tokenize/sentence_tokenize.py
indicnlp/transliterate/__init__.py
indicnlp/transliterate/acronym_transliterator.py
indicnlp/transliterate/script_unifier.py
indicnlp/transliterate/unicode_transliterate.py
indicnlp/urduhack/__init__.py
indicnlp/urduhack/normalization/__init__.py
indicnlp/urduhack/normalization/character.py
indicnlp/urduhack/normalization/regexes.py
indicnlp/urduhack/preprocessing/__init__.py
indicnlp/urduhack/preprocessing/character.py
indicnlp/urduhack/preprocessing/regexes.py
indicnlp/urduhack/preprocessing/util.py
indicnlp/urduhack/stop_words.py
indicnlp/urduhack/tokenization/__init__.py
indicnlp/urduhack/tokenization/eos.py
indicnlp/urduhack/tokenization/tokenizer.py
indicnlp/urduhack/urdu_characters.py
indic_nlp_library_itt-0.1.0.dist-info/LICENSE
indic_nlp_library_itt-0.1.0.dist-info/METADATA
indic_nlp_library_itt-0.1.0.dist-info/WHEEL
indic_nlp_library_itt-0.1.0.dist-info/RECORD
