Metadata-Version: 2.3
Name: indic-nlp-library-itt
Version: 0.1.0
Summary: The goal of the Indic NLP Library is to build Python based libraries for common  text processing and Natural Language Processing in Indian languages. This fork is specialized for IndicTrans2.
License: MIT
Author: varun230999@gmail.com
Requires-Python: >=3.8
Classifier: Programming Language :: Python :: 3
Classifier: License :: OSI Approved :: MIT License
Classifier: Operating System :: OS Independent
Requires-Dist: morfessor (>=2.0.6,<3.0.0)
Requires-Dist: numpy (>=2.2.5,<3.0.0)
Requires-Dist: pandas (>=2.2.3,<3.0.0)
Requires-Dist: sphinx-argparse (>=0.5.2,<0.6.0)
Requires-Dist: sphinx-rtd-theme (>=3.0.2,<4.0.0)
